aiohttp_zip_response/__init__.py
aiohttp_zip_response/py.typed
aiohttp_zip_response/zip_response.py
aiohttp_zip_response-2.4.0.dist-info/METADATA
aiohttp_zip_response-2.4.0.dist-info/WHEEL
aiohttp_zip_response-2.4.0.dist-info/licenses/LICENSE
aiohttp_zip_response-2.4.0.dist-info/RECORD
