Metadata-Version: 2.4
Name: aiohttp-zip-response
Version: 2.4.0
Summary: A AIOHTTP response class streaming a directory as ZIP archive
Project-URL: homepage, https://github.com/DoctorJohn/aiohttp-zip-response
Project-URL: repository, https://github.com/DoctorJohn/aiohttp-zip-response
Project-URL: documentation, https://github.com/DoctorJohn/aiohttp-zip-response
Author-email: Jonathan Ehwald <github@ehwald.info>
License: MIT
License-File: LICENSE
Classifier: Development Status :: 5 - Production/Stable
Classifier: Environment :: Web Environment
Classifier: Intended Audience :: Developers
Classifier: License :: OSI Approved :: MIT License
Classifier: Operating System :: OS Independent
Classifier: Programming Language :: Python
Classifier: Programming Language :: Python :: 3
Classifier: Programming Language :: Python :: 3.9
Classifier: Programming Language :: Python :: 3.10
Classifier: Programming Language :: Python :: 3.11
Classifier: Programming Language :: Python :: 3.12
Classifier: Programming Language :: Python :: 3.13
Classifier: Programming Language :: Python :: 3.14
Classifier: Topic :: Internet :: WWW/HTTP
Classifier: Topic :: Internet :: WWW/HTTP :: Dynamic Content
Classifier: Topic :: Software Development :: Libraries
Classifier: Topic :: Software Development :: Libraries :: Python Modules
Requires-Python: <4.0,>=3.9
Requires-Dist: aiohttp<4.0,>=3.9.5
Requires-Dist: stream-zip<0.1.0,>=0.0.83
